MANIFEST.in
README.txt
buildout.cfg
setup.py
docs/COPYRIGHT.txt
docs/HISTORY.txt
docs/LICENSE.txt
gpxtools/__init__.py
gpxtools/fixer.py
gpxtools/script.py
gpxtools/srtm.py
gpxtools.egg-info/PKG-INFO
gpxtools.egg-info/SOURCES.txt
gpxtools.egg-info/dependency_links.txt
gpxtools.egg-info/entry_points.txt
gpxtools.egg-info/not-zip-safe
gpxtools.egg-info/requires.txt
gpxtools.egg-info/top_level.txt