Metadata-Version: 1.0
Name: gpxtools
Version: 0.2.1
Summary: Command line tools useful to manipulate GPX files.
Home-page: http://lichota.pl/blog/topics/gpxtools
Author: Wojciech Lichota
Author-email: wojciech@lichota.pl
License: GPL
Keywords: GPS GPX SRTM
Platform: UNKNOWN
Classifier: Environment :: Console
Classifier: Intended Audience :: End Users/Desktop
Classifier: License :: OSI Approved :: GNU General Public License (GPL)
Classifier: Topic :: Scientific/Engineering :: GIS
Classifier: Topic :: Text Processing :: Markup :: XML
